LICENSE
MANIFEST.in
README.md
requirements.txt
setup.py
xpcspy/__init__.py
xpcspy.egg-info/PKG-INFO
xpcspy.egg-info/SOURCES.txt
xpcspy.egg-info/dependency_links.txt
xpcspy.egg-info/entry_points.txt
xpcspy.egg-info/requires.txt
xpcspy.egg-info/top_level.txt
xpcspy/../_agent.js
xpcspy/console/__init__.py
xpcspy/console/cli.py
xpcspy/lib/__init__.py
xpcspy/lib/types.py
xpcspy/utils/__init__.py
xpcspy/utils/agent.py